setup.cfg
setup.py
Schemer3.egg-info/PKG-INFO
Schemer3.egg-info/SOURCES.txt
Schemer3.egg-info/dependency_links.txt
Schemer3.egg-info/pbr.json
Schemer3.egg-info/top_level.txt
schemer/__init__.py
schemer/exceptions.py
schemer/extension_types.py
schemer/validators.py