Metadata-Version: 1.0
Name: Schemer3
Version: 0.2.11.post1
Summary: Powerful schema-based validation of Python dicts
Home-page: http://github.com/thekiba/schemer3
Author: Tom Leach
Author-email: tom@gc.io
License: BSD
Keywords: validation schema dict list
Platform: UNKNOWN
